ice/__init__.py
ice/dispatcher.py
ice/dto.py
ice/enums.py
ice/log.py
ice/_internal/__init__.py
ice/_internal/executor.py
ice/_internal/timeutil.py
ice/_internal/uuid.py
ice/cache/__init__.py
ice/cache/conf_cache.py
ice/cache/handler_cache.py
ice/client/__init__.py
ice/client/async_file_client.py
ice/client/file_client.py
ice/context/__init__.py
ice/context/context.py
ice/context/pack.py
ice/context/roam.py
ice/handler/__init__.py
ice/handler/handler.py
ice/leaf/__init__.py
ice/leaf/registry.py
ice/node/__init__.py
ice/node/base.py
ice/node/leaf.py
ice/node/relation.py
ice/relation/__init__.py
ice/relation/parallel.py
ice/relation/serial.py
ice_rules-2.0.1.dist-info/METADATA
ice_rules-2.0.1.dist-info/WHEEL
ice_rules-2.0.1.dist-info/top_level.txt
ice_rules-2.0.1.dist-info/RECORD
