Metadata-Version: 2.4
Name: ice-rules
Version: 2.0.1
Summary: Ice Rule Engine Python SDK
Author: waitmoon
License: Apache-2.0
Project-URL: Homepage, https://github.com/waitmoon/ice
Project-URL: Documentation, https://waitmoon.github.io/ice
Project-URL: Repository, https://github.com/waitmoon/ice
Keywords: ice,rule-engine,decision-engine
Classifier: Development Status :: 4 - Beta
Classifier: Intended Audience :: Developers
Classifier: License :: OSI Approved :: Apache Software License
Classifier: Programming Language :: Python :: 3
Classifier: Programming Language :: Python :: 3.11
Classifier: Programming Language :: Python :: 3.12
Classifier: Topic :: Software Development :: Libraries :: Python Modules
Requires-Python: >=3.11
